autogen_fargate_executor/__init__.py
autogen_fargate_executor/executor.py
autogen_fargate_executor-0.1.1.dist-info/LICENSE
autogen_fargate_executor-0.1.1.dist-info/METADATA
autogen_fargate_executor-0.1.1.dist-info/WHEEL
autogen_fargate_executor-0.1.1.dist-info/RECORD
