Metadata-Version: 2.1
Name: autogen-fargate-executor
Version: 0.1.1
Summary: AWS Fargate code executor for AutoGen - Run code securely and scale beyond local resources
Home-page: https://github.com/imankamyabi/autogen-fargate-executor
License: MIT
Keywords: autogen,aws,fargate,executor,serverless,ai,code-execution
Author: Iman Kamyabi
Author-email: engkamyabi@gmail.com
Requires-Python: >=3.8,<4.0
Classifier: Development Status :: 4 - Beta
Classifier: Intended Audience :: Developers
Classifier: License :: OSI Approved :: MIT License
Classifier: Programming Language :: Python :: 3
Classifier: Programming Language :: Python :: 3.8
Classifier: Programming Language :: Python :: 3.9
Classifier: Programming Language :: Python :: 3.10
Classifier: Programming Language :: Python :: 3.11
Classifier: Programming Language :: Python :: 3.12
Classifier: Programming Language :: Python :: 3.13
Classifier: Topic :: Software Development :: Libraries :: Application Frameworks
Classifier: Topic :: Software Development :: Libraries :: Python Modules
Classifier: Topic :: System :: Distributed Computing
Requires-Dist: autogen-agentchat (>=0.2.38,<0.3.0)
Requires-Dist: boto3 (>=1.34.0,<2.0.0)
Requires-Dist: flaml[automl] (>=2.3.2,<3.0.0)
Project-URL: Documentation, https://github.com/imankamyabi/autogen-fargate-executor#readme
Project-URL: Repository, https://github.com/imankamyabi/autogen-fargate-executor
